 

 {
     "matches": [
        {
        "utcStartSeconds":1598253691,
        "utcEndSeconds":1598255254,
        "map":"mp_don3",
        "mode":"br_brduos",
        "matchID":"16190551183871537712",
        "duration":1563000,
        "playlistName":null,
        "version":1,
        "gameType":"wz",
        "playerCount":150,
        "playerStats":{
            "clutchKills":28,
            "kills":175,
            "medalXp":0,
            "matchXp":4129,
            "scoreXp":100,
            "wallBangs":0,
            "score":10096,
            "totalXp":4229,
            "headshots":0,
            "assists":0,
            "challengeXp":0,
            "rank":54,
            "scorePerMinute":11.25703564727955,
            "distanceTraveled":314987.66,
            "teamSurvivalTime":444480,
            "deaths":67,
            "kdRatio":0,
            "objectiveBrMissionPickupTablet":1,
            "bonusXp":0,
            "objectiveReviver":46,
            "gulagDeaths":22,
            "timePlayed":533,
            "executions":0,
            "gulagKills":16,
            "nearmisses":0,
            "percentTimeMoving":48.780487,
            "miscXp":0,
            "longestStreak":0,
            "teamPlacement":52,
            "damageDone":116,
            "damageTaken":465
            } 
        },
        {
            "utcStartSeconds":1598251923,
            "utcEndSeconds":1598253546,
            "map":"mp_don3",
            "mode":"br_brtrios",
            "matchID":"18041390293838477337",
            "duration":1623000,
            "playlistName":null,
            "version":1,
            "gameType":"wz",
            "playerCount":155,
            "playerStats":{
                "clutchKills":38,
                "kills":108,
                "medalXp":325,
                "objectiveTeamWiped":3,
                "objectiveLastStandKill":7,
                "matchXp":13399,
                "scoreXp":16250,
                "wallBangs":0,
                "score":11050,
                "totalXp":32336,
                "headshots":0,
                "assists":0,
                "challengeXp":0,
                "rank":54,
                "scorePerMinute":388.8563049853372,
                "distanceTraveled":422070.44,
                "teamSurvivalTime":1577760,
                "deaths":45,
                "objectiveBrDownEnemyCircle4":1,
                "objectiveBrDownEnemyCircle3":3,
                "kdRatio":5,
                "objectiveBrDownEnemyCircle1":5,
                "objectiveBrMissionPickupTablet":4,
                "bonusXp":0,
                "objectiveReviver":21,
                "objectiveBrKioskBuy":3,
                "objectiveBrDownEnemyCircle6":3,
                "gulagDeaths":22,
                "timePlayed":1705,
                "executions":0,
                "gulagKills":34,
                "nearmisses":0,
                "objectiveBrCacheOpen":9,
                "percentTimeMoving":91.28763,
                "miscXp":0,
                "objectiveTrophyDefense":1,
                "longestStreak":7,
                "teamPlacement":72,
                "damageDone":4228,
                "damageTaken":675
            } 
        },{
            "utcStartSeconds":1598250900,
            "utcEndSeconds":1598252485,
            "map":"mp_don3",
            "mode":"br_brtrios",
            "matchID":"9224712587785081928",
            "duration":1585000,
            "playlistName":null,
            "version":1,
            "gameType":"wz",
            "playerCount":150,
            "playerStats":{
                "clutchKills":29,
                "kills":201,
                "medalXp":20,
                "objectiveLastStandKill":1,
                "matchXp":7543,
                "scoreXp":8225,
                "wallBangs":0,
                "score":3975,
                "totalXp":15840,
                "headshots":1,
                "assists":0,
                "challengeXp":0,
                "rank":54,
                "scorePerMinute":247.15025906735752,
                "distanceTraveled":608978.1,
                "teamSurvivalTime":894048,
                "deaths":39,
                "kdRatio":1,
                "objectiveBrDownEnemyCircle1":1,
                "objectiveBrMissionPickupTablet":5,
                "bonusXp":0,
                "objectiveReviver":34,
                "objectiveBrKioskBuy":3,
                "gulagDeaths":19,
                "timePlayed":965,
                "executions":0,
                "gulagKills":34,
                "nearmisses":0,
                "objectiveBrCacheOpen":7,
                "percentTimeMoving":95.37246,
                "miscXp":0,
                "longestStreak":1,
                "teamPlacement":21,
                "damageDone":1094,
                "damageTaken":423
            }
        },{
            "utcStartSeconds":1598249209,
            "utcEndSeconds":1598250810,
            "map":"mp_don3",
            "mode":"br_brduos",
            "matchID":"14975360524801631551",
            "duration":1601000,
            "playlistName":null,
            "version":1,
            "gameType":"wz",
            "playerCount":147,
            "playerStats":{
                "clutchKills":41,
                "kills":198,
                "medalXp":50,
                "objectiveLastStandKill":3,
                "matchXp":12494,
                "scoreXp":10575,
                "wallBangs":0,
                "score":8575,
                "totalXp":23731,
                "headshots":0,
                "assists":0,
                "challengeXp":0,
                "rank":54,
                "scorePerMinute":325.0157927984839,
                "distanceTraveled":568344.9,
                "teamSurvivalTime":1506096,
                "deaths":28,
                "kdRatio":2.5,
                "objectiveBrDownEnemyCircle1":2,
                "objectiveBrMissionPickupTablet":3,
                "bonusXp":0,
                "objectiveReviver":43,
                "objectiveBrKioskBuy":8,
                "gulagDeaths":66,
                "objectiveBrDownEnemyCircle5":1,
                "timePlayed":1583,
                "executions":0,
                "gulagKills":37,
                "nearmisses":0,
                "objectiveBrCacheOpen":4,
                "percentTimeMoving":85.67604,
                "miscXp":0,
                "longestStreak":3,
                "teamPlacement":34,
                "damageDone":1838,
                "damageTaken":777
            }
        },{
            "utcStartSeconds":1598247306,
            "utcEndSeconds":1598248912,
            "map":"mp_don3",
            "mode":"br_brduos",
            "matchID":"14021482141711537035",
            "duration":1606000,
            "playlistName":null,
            "version":1,
            "gameType":"wz",
            "playerCount":151,
            "playerStats":{
                "clutchKills":22,
                "kills":181,
                "medalXp":880,
                "objectiveTeamWiped":4,
                "objectiveLastStandKill":9,
                "matchXp":12524,
                "scoreXp":18950,
                "wallBangs":0,
                "score":16950,
                "totalXp":33894,
                "headshots":4,
                "assists":0,
                "challengeXp":0,
                "rank":54,
                "scorePerMinute":665.1406147809025,
                "objectiveDestroyedVehicleMedium":1,
                "distanceTraveled":535449.75,
                "teamSurvivalTime":1439952,
                "deaths":33,
                "objectiveMunitionsBoxTeammateUsed":1,
                "objectiveBrDownEnemyCircle4":2,
                "kdRatio":11,
                "objectiveBrDownEnemyCircle2":1,
                "objectiveBrDownEnemyCircle1":8,
                "objectiveBrMissionPickupTablet":4,
                "bonusXp":0,
                "objectiveReviver":23,
                "objectiveBrKioskBuy":10,
                "gulagDeaths":55,
                "objectiveBrDownEnemyCircle5":1,
                "timePlayed":1529,
                "executions":0,
                "gulagKills":67,
                "nearmisses":0,
                "objectiveBrCacheOpen":5,
                "percentTimeMoving":96.94232,
                "miscXp":0,
                "objectiveTrophyDefense":2,
                "longestStreak":12,
                "teamPlacement":46,
                "damageDone":3787,
                "damageTaken":615
            }
        }
    ]
}


